rmgintegration/__init__.py
rmgintegration/integration.py
numintegration-2.0.dist-info/LICENSE.TXT
numintegration-2.0.dist-info/METADATA
numintegration-2.0.dist-info/WHEEL
numintegration-2.0.dist-info/top_level.txt
numintegration-2.0.dist-info/RECORD
